territory_python_scanner/.__init__.py.un~
territory_python_scanner/__init__.py
territory_python_scanner/__main__.py
territory_python_scanner/scanner.py
territory_python_scanner/timeout.py
territory_python_scanner/uim_pb2.py
territory_python_scanner/writer.py
territory_python_scanner-1.3.1.dist-info/licenses/LICENSE
territory_python_scanner-1.3.1.dist-info/WHEEL
territory_python_scanner-1.3.1.dist-info/METADATA
territory_python_scanner-1.3.1.dist-info/RECORD
